Workbook

Sheet Income Statement
A1: RIL — INCOME STATEMENT (₹ Cr)
A3: Year | B3: FY2025(A) | C3: FY2026(P) | D3: FY2027(P) | E3: FY2028(P) | F3: FY2029(P) | G3: FY2030(P)
A4: Revenue | B4: 1071174 | C4: =B4*(1+Assumptions!B3) -> 1156867.9 | D4: =C4*(1 +Assumptions!C3) -> 1249417.4 | E4: =D4*(1+Assumptions!D3) -> 1343123.7 | F4: =E4*(1+Assumptions!E3) -> 1437142.3 | G4: =F4*(1+Assumptions!F3) -> 1537742.3
A5: Revenue Growth % | C5: =Assumptions!B3 -> 0.08 | D5: =Assumptions!C3 -> 0.08 | E5: =Assumptions!D3 -> 0.075 | F5: =Assumptions!E3 -> 0.07 | G5: =Assumptions!F3 -> 0.07
A6: Operating Expenses | B6: =B4-B7 -> 887752 | C6: =C4-C7 -> 948631.69 | D6: =D4-D7 -> 1018275.1 | E6: =E4-E7 -> 1087930.2 | F6: =F4-F7 -> 1164085.3 | G6: =G4-G7 -> 1237882.5
A7: EBITDA | B7: 183422 | C7: =C4*Assumptions!B4 -> 208236.23 | D7: =D4*Assumptions!C4 -> 231142.21 | E7: =E4*Assumptions!D4 -> 255193.49 | F7: =F4*Assumptions!E4 -> 273057.04 | G7: =G4*Assumptions!F4 -> 299859.74
A8: EBITDA Margin % | B8: =(B4-B6)/B6 -> 0.20661401 | C8: =Assumptions!B4 -> 0.18 | D8: =Assumptions!C4 -> 0.185 | E8: =Assumptions!D4 -> 0.19 | F8: =Assumptions!E4 -> 0.19 | G8: =Assumptions!F4 -> 0.195
A9: Less: D&A | B9: 53136 | C9: =C4*Assumptions!B5 -> 57843.396 | D9: =D4*Assumptions!C5 -> 62470.868 | E9: =E4*Assumptions!D5 -> 67156.183 | F9: =F4*Assumptions!E5 -> 71857.116 | G9: =G4*Assumptions!F5 -> 76887.114
A10: EBIT | B10: =B7-B9 -> 130286 | C10: =C7-C9 -> 150392.83 | D10: =D7-D9 -> 168671.34 | E10: =E7-E9 -> 188037.31 | F10: =F7-F9 -> 201199.92 | G10: =G7-G9 -> 222972.63
A11: Less: Interest | B11: 24269 | C11: =C4*Assumptions!B6 -> 26029.528 | D11: =D4*Assumptions!C6 -> 27487.182 | E11: =E4*Assumptions!D6 -> 28205.597 | F11: =F4*Assumptions!E6 -> 28742.846 | G11: =G4*Assumptions!F6 -> 30754.845
A12: EBT (Pre-Tax) | B12: =B10-B11 -> 106017 | C12: =C10-C11 -> 124363.3 | D12: =D10-D11 -> 141184.16 | E12: =E10-E11 -> 159831.71 | F12: =F10-F11 -> 172457.08 | G12: =G10-G11 -> 192217.78
A13: Less: Tax | B13: 25230 | C13: =C12*Assumptions!B7 -> 29225.376 | D13: =D12*Assumptions!C7 -> 33178.278 | E13: =E12*Assumptions!D7 -> 37560.453 | F13: =F12*Assumptions!E7 -> 40527.413 | G13: =G12*Assumptions!F7 -> 45171.179
A14: Net Income | B14: =B12-B13 -> 80787 | C14: =C12-C13 -> 95137.926 | D14: =D12-D13 -> 108005.88 | E14: =E12-E13 -> 122271.26 | F14: =F12-F13 -> 131929.66 | G14: =G12-G13 -> 147046.6

Sheet Cash Flow
A1: RIL — CASH FLOW STATEMENT (₹ Cr)
A3: Year | B3: FY2025(A) | C3: FY2026(P) | D3: FY2027(P) | E3: FY2028(P) | F3: FY2029(P) | G3: FY2030(P)
A4: OPERATING ACTIVITIES
A5: Net Income | C5: ='Income Statement'!C14 -> 95137.926 | D5: ='Income Statement'!D14 -> 108005.88 | E5: ='Income Statement'!E14 -> 122271.26 | F5: ='Income Statement'!F14 -> 131929.66 | G5: ='Income Statement'!G14 -> 147046.6
A6: Add: D&A | C6: ='Income Statement'!C9 -> 57843.396 | D6: ='Income Statement'!D9 -> 62470.868 | E6: ='Income Statement'!E9 -> 67156.183 | F6: ='Income Statement'!F9 -> 71857.116 | G6: ='Income Statement'!G9 -> 76887.114
A7: Change in Working Capital | C7: =-('Balance Sheet'!C6-'Balance Sheet'!B6)+('Balance Sheet'!C12-'Balance Sheet'!B12) -> 14701.52 | D7: =-('Balance Sheet'!D6-'Balance Sheet'!C6)+('Balance Sheet'!D12-'Balance Sheet'!C12) -> 15877.642 | E7: =-('Balance Sheet'!E6-'Balance Sheet'!D6)+('Balance Sheet'!E12-'Balance Sheet'!D12) -> 16076.112 | F7: =-('Balance Sheet'!F6-'Balance Sheet'!E6)+('Balance Sheet'!F12-'Balance Sheet'!E12) -> 16129.699 | G7: =-('Balance Sheet'!G6-'Balance Sheet'!F6)+('Balance Sheet'!G12-'Balance Sheet'!F12) -> 17258.778
A8: Cash from Operations | C8: =C5+C6+C7 -> 167682.84 | D8: =D5+D6+D7 -> 186354.39 | E8: =E5+E6+E7 -> 205503.56 | F8: =F5+F6+F7 -> 219916.48 | G8: =G5+G6+G7 -> 241192.5
A10: INVESTING ACTIVITIES
A11: Less: Capex | C11: =-'Income Statement'!C4*Assumptions!B8 -> -138824.15 | D11: =-'Income Statement'!D4*Assumptions!C8 -> -143683 | E11: =-'Income Statement'!E4*Assumptions!D8 -> -147743.6 | F11: =-'Income Statement'!F4*Assumptions!E8 -> -150899.94 | G11: =-'Income Statement'!G4*Assumptions!F8 -> -153774.23
A12: Change in Other LT Assets | C12: =-('Balance Sheet'!C8-'Balance Sheet'!B8) -> -47843.12 | D12: =-('Balance Sheet'!D8-'Balance Sheet'!C8) -> -51670.57 | E12: =-('Balance Sheet'!E8-'Balance Sheet'!D8) -> -52316.452 | F12: =-('Balance Sheet'!F8-'Balance Sheet'!E8) -> -52490.84 | G12: =-('Balance Sheet'!G8-'Balance Sheet'!F8) -> -56165.199
A13: Cash from Investing | C13: =C11+C12 -> -186667.27 | D13: =D11+D12 -> -195353.57 | E13: =E11+E12 -> -200060.05 | F13: =F11+F12 -> -203390.78 | G13: =G11+G12 -> -209939.43
A15: FINANCING ACTIVITIES
A16: Change in Debt | C16: 0 | D16: 0 | E16: 0 | F16: 0 | G16: 0
A17: Less: Dividends | C17: =-'Income Statement'!C14*0.1 -> -9513.7926 | D17: =-'Income Statement'!D14*0.1 -> -10800.588 | E17: =-'Income Statement'!E14*0.1 -> -12227.126 | F17: =-'Income Statement'!F14*0.1 -> -13192.966 | G17: =-'Income Statement'!G14*0.1 -> -14704.66
A18: Change in Other LT Liabilities | C18: ='Balance Sheet'!C14-'Balance Sheet'!B14 -> 19988.72 | D18: ='Balance Sheet'!D14-'Balance Sheet'!C14 -> 21587.818 | E18: ='Balance Sheet'!E14-'Balance Sheet'!D14 -> 21857.665 | F18: ='Balance Sheet'!F14-'Balance Sheet'!E14 -> 21930.524 | G18: ='Balance Sheet'!G14-'Balance Sheet'!F14 -> 23465.661
A19: Cash from Financing | C19: =C16+C17+C18 -> 10474.927 | D19: =D16+D17+D18 -> 10787.229 | E19: =E16+E17+E18 -> 9630.5391 | F19: =F16+F17+F18 -> 8737.5578 | G19: =G16+G17+G18 -> 8761.0004
A21: Net Change in Cash | C21: =C8+C13+C19 -> -8509.5014 | D21: =D8+D13+D19 -> 1788.0564 | E21: =E8+E13+E19 -> 15074.042 | F21: =F8+F13+F19 -> 25263.254 | G21: =G8+G13+G19 -> 40014.071
A22: Beginning Cash | C22: ='Balance Sheet'!B5 -> 229302 | D22: ='Balance Sheet'!C5 -> 220792.5 | E22: ='Balance Sheet'!D5 -> 222580.56 | F22: ='Balance Sheet'!E5 -> 237654.6 | G22: ='Balance Sheet'!F5 -> 262917.85
A23: Ending Cash | C23: =C22+C21 -> 220792.5 | D23: =D22+D21 -> 222580.56 | E23: =E22+E21 -> 237654.6 | F23: =F22+F21 -> 262917.85 | G23: =G22+G21 -> 302931.92

Sheet Balance Sheet
A1: RIL — BALANCE SHEET (₹ Cr)
A3: Year | B3: FY2025(A) | C3: FY2026(P) | D3: FY2027(P) | E3: FY2028(P) | F3: FY2029(P) | G3: FY2030(P)
A4: ASSETS
A5: Cash & Equivalents | B5: 229302 | C5: ='Cash Flow'!C23 -> 220792.5 | D5: ='Cash Flow'!D23 -> 222580.56 | E5: ='Cash Flow'!E23 -> 237654.6 | F5: ='Cash Flow'!F23 -> 262917.85 | G5: ='Cash Flow'!G23 -> 302931.92
A6: Other Current Assets | B6: 269968 | C6: =B6*(1+'Income Statement'!C5) -> 291565.44 | D6: =C6*(1+'Income Statement'!D5) -> 314890.68 | E6: =D6*(1+'Income Statement'!E5) -> 338507.48 | F6: =E6*(1+'Income Statement'!F5) -> 362203 | G6: =F6*(1+'Income Statement'!G5) -> 387557.21
A7: Net Fixed Assets (PP&E) | B7: 852812 | C7: =B7+'Income Statement'!C4*Assumptions!B8-'Income Statement'!C9 -> 933792.75 | D7: =C7+'Income Statement'!D4*Assumptions!C8-'Income Statement'!D9 -> 1015004.9 | E7: =D7+'Income Statement'!E4*Assumptions!D8-'Income Statement'!E9 -> 1095592.3 | F7: =E7+'Income Statement'!F4*Assumptions!E8-'Income Statement'!F9 -> 1174635.1 | G7: =F7+'Income Statement'!G4*Assumptions!F8-'Income Statement'!G9 -> 1251522.2
A8: Other Long-Term Assets | B8: 598039 | C8: =B8*(1+'Income Statement'!C5) -> 645882.12 | D8: =C8*(1+'Income Statement'!D5) -> 697552.69 | E8: =D8*(1+'Income Statement'!E5) -> 749869.14 | F8: =E8*(1+'Income Statement'!F5) -> 802359.98 | G8: =F8*(1+'Income Statement'!G5) -> 858525.18
A9: Total Assets | B9: =B5+B6+B7+B8 -> 1950121 | C9: =C5+C6+C7+C8 -> 2092032.8 | D9: =D5+D6+D7+D8 -> 2250028.8 | E9: =E5+E6+E7+E8 -> 2421623.5 | F9: =F5+F6+F7+F8 -> 2602116 | G9: =G5+G6+G7+G8 -> 2800536.6
A11: LIABILITIES
A12: Current Liabilities | B12: 453737 | C12: =B12*(1+'Income Statement'!C5) -> 490035.96 | D12: =C12*(1+'Income Statement'!D5) -> 529238.84 | E12: =D12*(1+'Income Statement'!E5) -> 568931.75 | F12: =E12*(1+'Income Statement'!F5) -> 608756.97 | G12: =F12*(1+'Income Statement'!G5) -> 651369.96
A13: Debt | B13: 236899 | C13: =B13 -> 236899 | D13: =C13 -> 236899 | E13: =D13 -> 236899 | F13: =E13 -> 236899 | G13: =F13 -> 236899
A14: Other Long-Term Liabilities | B14: 249859 | C14: =B14*(1+'Income Statement'!C5) -> 269847.72 | D14: =C14*(1+'Income Statement'!D5) -> 291435.54 | E14: =D14*(1+'Income Statement'!E5) -> 313293.2 | F14: =E14*(1+'Income Statement'!F5) -> 335223.73 | G14: =F14*(1+'Income Statement'!G5) -> 358689.39
A15: Total Liabilities | B15: =B12+B13+B14 -> 940495 | C15: =C12+C13+C14 -> 996782.68 | D15: =D12+D13+D14 -> 1057573.4 | E15: =E12+E13+E14 -> 1119124 | F15: =F12+F13+F14 -> 1180879.7 | G15: =G12+G13+G14 -> 1246958.3
A17: EQUITY
A18: Share Capital | B18: 106636 | C18: 106636 | D18: 106636 | E18: 106636 | F18: 106636 | G18: 106636
A19: Retained Earnings | B19: 902990 | C19: =B19+'Income Statement'!C14*(1-0.1) -> 988614.13 | D19: =C19+'Income Statement'!D14*(1-0.1) -> 1085819.4 | E19: =D19+'Income Statement'!E14*(1-0.1) -> 1195863.6 | F19: =E19+'Income Statement'!F14*(1-0.1) -> 1314600.3 | G19: =F19+'Income Statement'!G14*(1-0.1) -> 1446942.2
A20: Total Equity | B20: =B18+B19 -> 1009626 | C20: =C18+C19 -> 1095250.1 | D20: =D18+D19 -> 1192455.4 | E20: =E18+E19 -> 1302499.6 | F20: =F18+F19 -> 1421236.3 | G20: =G18+G19 -> 1553578.2
A22: Total Liab. + Equity | B22: =B15+B20 -> 1950121 | C22: =C15+C20 -> 2092032.8 | D22: =D15+D20 -> 2250028.8 | E22: =E15+E20 -> 2421623.5 | F22: =F15+F20 -> 2602116 | G22: =G15+G20 -> 2800536.6
A23: Check (Assets − L&E) | B23: =B9-B22 -> 0 | C23: =C9-C22 -> 0 | D23: =D9-D22 -> 0 | E23: =E9-E22 -> 0 | F23: =F9-F22 -> 0 | G23: =G9-G22 -> 0

Sheet Assumptions
A1: INCOME STATEMENT ASSUMPTIONS
A2: Driver | B2: FY2026 | C2: FY2027 | D2: FY2028 | E2: FY2029 | F2: FY2030
A3: Revenue Growth % | B3: 0.08 | C3: 0.08 | D3: 0.075 | E3: 0.07 | F3: 0.07
A4: EBITDA Margin % | B4: 0.18 | C4: 0.185 | D4: 0.19 | E4: 0.19 | F4: 0.195
A5: D&A (% of Revenue) | B5: 0.05 | C5: 0.05 | D5: 0.05 | E5: 0.05 | F5: 0.05
A6: Interest (% of Revenue) | B6: 0.0225 | C6: 0.022 | D6: 0.021 | E6: 0.02 | F6: 0.02
A7: Tax Rate % | B7: 0.235 | C7: 0.235 | D7: 0.235 | E7: 0.235 | F7: 0.235
A8: Capex (% of Revenue) | B8: 0.12 | C8: 0.115 | D8: 0.11 | E8: 0.105 | F8: 0.1
